STCAT/STCAT.py
STCAT/__init__.py
STCAT/annotate.py
STCAT/classifier.py
STCAT/logger.py
STCAT/models.py
STCAT/data/T_cell.pkl
STCAT/data/cd4.pkl
STCAT/data/cd8.pkl
STCAT/data/marker_CD4.txt
STCAT/data/marker_CD8.txt
STCAT-1.0.8.dist-info/METADATA
STCAT-1.0.8.dist-info/WHEEL
STCAT-1.0.8.dist-info/top_level.txt
STCAT-1.0.8.dist-info/RECORD
