Metadata-Version: 2.1
Name: STCAT
Version: 1.0.8
Summary: An automated T cell type annotation tool for scRNA-seq datasets.
Home-page: https://github.com/GuoBioinfoLab/STCAT
License: MIT
Classifier: Programming Language :: Python :: 3.8
Classifier: Operating System :: POSIX :: Linux
Classifier: Intended Audience :: Science/Research
Classifier: Topic :: Scientific/Engineering :: Bio-Informatics
Requires-Python: >=3.8
Requires-Dist: anndata ==0.10.9
Requires-Dist: array-api-compat ==1.10.0
Requires-Dist: click ==8.1.8
Requires-Dist: contourpy ==1.3.0
Requires-Dist: cycler ==0.12.1
Requires-Dist: et-xmlfile ==2.0.0
Requires-Dist: exceptiongroup ==1.2.2
Requires-Dist: fonttools ==4.55.3
Requires-Dist: h5py ==3.12.1
Requires-Dist: igraph ==0.11.8
Requires-Dist: importlib-resources ==6.5.2
Requires-Dist: joblib ==1.4.2
Requires-Dist: kiwisolver ==1.4.7
Requires-Dist: leidenalg ==0.10.2
Requires-Dist: llvmlite ==0.43.0
Requires-Dist: matplotlib ==3.9.4
Requires-Dist: natsort ==8.4.0
Requires-Dist: networkx ==3.2.1
Requires-Dist: numba ==0.60.0
Requires-Dist: numpy ==1.26.4
Requires-Dist: openpyxl ==3.1.5
Requires-Dist: packaging ==24.2
Requires-Dist: pandas ==2.2.0
Requires-Dist: patsy ==1.0.1
Requires-Dist: pillow ==11.1.0
Requires-Dist: pynndescent ==0.5.13
Requires-Dist: pyparsing ==3.2.1
Requires-Dist: python-dateutil ==2.9.0.post0
Requires-Dist: pytz ==2024.2
Requires-Dist: scanpy ==1.9.3
Requires-Dist: scikit-learn ==1.2.2
Requires-Dist: scipy ==1.13.1
Requires-Dist: seaborn ==0.13.2
Requires-Dist: session-info ==1.0.0
Requires-Dist: six ==1.17.0
Requires-Dist: statsmodels ==0.14.4
Requires-Dist: stdlib-list ==0.11.0
Requires-Dist: texttable ==1.7.0
Requires-Dist: threadpoolctl ==3.5.0
Requires-Dist: tqdm ==4.67.1
Requires-Dist: tzdata ==2024.2
Requires-Dist: umap-learn ==0.5.7
Requires-Dist: zipp ==3.21.0
